FormatFuncs/__init__.py
FormatFuncs/formatfuncs.py
formatfuncs_Captain_William-0.1.1.dist-info/LICENSE.txt
formatfuncs_Captain_William-0.1.1.dist-info/METADATA
formatfuncs_Captain_William-0.1.1.dist-info/WHEEL
formatfuncs_Captain_William-0.1.1.dist-info/top_level.txt
formatfuncs_Captain_William-0.1.1.dist-info/RECORD
