Metadata-Version: 2.1
Name: formatfuncs-Captain-William
Version: 0.1.1
Summary: Functions to format strings
Home-page: https://github.com/The-Captain-William/FormatFuncs
Author: William Rivera
Author-email: william.r.2048@gmail.com
Classifier: Programming Language :: Python :: 3
Classifier: License :: OSI Approved :: MIT License
Classifier: Operating System :: OS Independent
Requires-Python: >=3.8
License-File: LICENSE.txt
